grass_wrapper/__init__.py
grass_wrapper/BigQuery/__init__.py
grass_wrapper/BigQuery/client.py
grass_wrapper/Bybit/__init__.py
grass_wrapper/Bybit/client.py
grass_wrapper/CoinGlass/__init__.py
grass_wrapper/CoinGlass/client.py
grass_wrapper/DuckDB/__init__.py
grass_wrapper/DuckDB/client.py
grass_wrapper-0.4.0.dist-info/METADATA
grass_wrapper-0.4.0.dist-info/WHEEL
grass_wrapper-0.4.0.dist-info/RECORD
