Metadata-Version: 2.4
Name: grass-wrapper
Version: 0.4.0
Summary: General purpose Python wrapper utilities
Project-URL: Source, https://github.com/grass-firm/grass-wrapper
Project-URL: Bug Tracker, https://github.com/grass-firm/grass-wrapper/issues
Project-URL: Documentation, https://github.com/grass-firm/grass-wrapper#readme
License: MIT
Classifier: License :: OSI Approved :: MIT License
Classifier: Operating System :: OS Independent
Classifier: Programming Language :: Python :: 3
Classifier: Programming Language :: Python :: 3 :: Only
Requires-Python: >=3.10
Requires-Dist: duckdb>=1.4.0
Requires-Dist: google-cloud-bigquery>=3.35.0
Requires-Dist: pandas>=2.2.0
Requires-Dist: requests>=2.32.0
Provides-Extra: dev
Requires-Dist: black; extra == 'dev'
Requires-Dist: build; extra == 'dev'
Requires-Dist: pytest; extra == 'dev'
Requires-Dist: ruff; extra == 'dev'
Requires-Dist: twine; extra == 'dev'
